{
  "peaked": {
    "url": "https://pbs.twimg.com/media/FhIBPX7XwAIrrtP?format=jpg&name=4096x4096",
    "lines": [
      "** Reddit Adjusted Fantasy Football Trade Values Week 10.1 ** @",
      "Analysis type: 4 Point 1QB 1.0PPR",
      "u/PeakedinHighSkool Updated: 2211090630",
      "Running Back Wide Receiver Tight End Quarterback",
      "Trade Value Player Name Trend Player Name Trend Player Name Trend Player Name Trend",
      "Tier 1",
      "76.0 Christian McCaffrey",
      "74.5 Austin Ekeler",
      "73.0 Derrick Henry",
      "71.0 Cooper Kupp 5.0",
      "69.5 Saquon Barkley",
      "68.0 Stefon Diggs",
      "66.0 Justin Jefferson",
      "64.5 Tyreek Hill",
      "63.0 Travis Kelce",
      "61.5 Nick Chubb",
      "Tier 2",
      "60.0 Alvin Kamara",
      "59.0 Travis Etienne Jr.",
      "57.5 Davante Adams",
      "56.0 AJ. Brown",
      "54.5 Jaylen Waddle",
      "53.5 DeAndre Hopkins",
      "52.0 Josh Jacobs",
      "51.0 Dalvin Cook",
      "Tier 3",
      "49.5 Joe Mixon",
      "48.5 Kenneth Walker III",
      "47.0 Amon-Ra St. Brown =",
      "46.0 CeeDee Lamb",
      "45.0 Mark Andrews",
      "44.0 Mike Evans 40",
      "43.0 Rhamondre Stevenson 40",
      "42.0 Tee Higgins",
      "41.0 Dameon Pierce 40",
      "40.0 Chris Olave",
      "Tier 4",
      "39.0 D'Andre Swift =",
      "38.0 Miles Sanders",
      "37.0 Aaron Jones 7.0",
      "36.0 DK Metcalf",
      "35.0 Jonathan Taylor",
      "34.5 Amari Cooper (00",
      "33.5 Leonard Fournette 25",
      "32.5 Josh Allen 257",
      "32.0 Chris Godwin",
      "31.0 Tyler Lockett",
      "30.5 George Kittle AIS)",
      "29.5 Tony Pollard 30",
      "Tier 5",
      "29.0 Deebo Samuel",
      "28.0 Dallas Goedert 05",
      "27.5 Najee Harris",
      "27.0 Cordarrelle Patterson [ERS",
      "26.5 JuJu Smith-Schuster",
      "25.5 Ezekiel Elliott",
      "25.0 Terry McLaurin",
      "24.5 James Conner 60",
      "24.0 Christian Kirk",
      "23.5 Jamaal Williams",
      "23.0 Zach Ertz",
      "Tier 6",
      "22.5 Diontae Johnson",
      "22.0 Ja'Marr Chase eS)",
      "21.5 DJ Moore",
      "21.0 Michael Pittman Jr. -8.0",
      "20.5 David Montgomery",
      "20.0 Jalen Hurts 00",
      "19.5 DeVonta Smith",
      "19.0 Patrick Mahomes II 20 —",
      "18.5 Michael Carter 35 Gabe Davis",
      "18.0 Jakobi Meyers",
      "17.5 Kareem Hunt",
      "17.0 Devin Singletary",
      "17.0 Raheem Mostert",
      "16.5 Khalil Herbert",
      "16.0 Allen Lazard 3.0 Lamar Jackson 05",
      "Tier 7",
      "15.5 Jeff Wilson Jr.",
      "15.0 D'Onta Foreman 1.0 TJ. Hockenson 05",
      "14.5 Antonio Gibson Brandon Aiyuk",
      "14.0 Pat Freiermuth",
      "13.5 Jerry Jeudy 1.0",
      "13.5 Keenan Allen ae)",
      "13.0 AJ Dillon",
      "13.0 James Robinson",
      "12.5 Courtland Sutton",
      "12.5 Garrett Wilson",
      "12.0 Tyler Boyd Clyde Edwards-Helaire",
      "12.0 Melvin Gordon III",
      "11.5 Rondale Moore Kyler Murray",
      "11.0 Curtis Samuel Joe Burrow",
      "10.5 George Pickens Tua Tagovailoa",
      "10.0 Gus Edwards = Brandin Cooks",
      "10.0 Rachaad White",
      "Tier 8",
      "9.5 Adam Thielen Justin Herbert",
      "9.0 Darnell Mooney Brian Robinson Jr.",
      "8.5 Damien Harris Mike Williams",
      "Tier 9",
      "8.0 Tyler Allgeier 20 | Gerald Everett [ISMN Justin Fields",
      "7.5 Kyle Pitts 0: Dak Prescott",
      "7.0 Greg Dulcich [gg Kirk Cousins",
      "6.5 Isiah Pacheco 5",
      "6.5 Kenyan Drake 7.0",
      "6.0 Chuba Hubbard Drake London",
      "5.5 Darrell Henderson Jr.",
      "Tier 10",
      "5.0 Geno Smith =",
      "5.0 Tom Brady",
      "4.5 Devin Duvernay",
      "4.5 WanDale Robinson",
      "4.0 Michael Gallup",
      "3.5 Latavius Murray =",
      "3.5 Nyheim Hines",
      "3.0 Dalton Schultz 05",
      "2.5 Alexander Mattison Joshua Palmer",
      "Tier 11",
      "2.0 Tyler Higbee",
      "1.5 Eno Benjamin 55 |",
      "1.0 Marquise Brown",
      "0.5 Chase Claypool",
      "0.5 Donovan Peoples-Jones",
      "\f"
    ]
  },
  "teams": [
    {
      "name": "Ek's Gonna Give It To Ya",
      "players": [
        "Austin Ekeler",
        "Stefon Diggs",
        "Nick Chubb",
        "Tee Higgins",
        "Courtland Sutton",
        "Allen Lazard",
        "Tyler Boyd",
        "Justin Tucker",
        "Raheem Mostert",
        "Tyler Allgeier",
        "Josh Allen",
        "DJ Moore",
        "Chiefs D/ST",
        "Jason Sanders",
        "Dalton Schultz",
        "Treylon Burks",
        "Trevor Lawrence"
      ]
    },
    {
      "name": "Team Silver Finger",
      "players": [
        "Derrick Henry",
        "Ezekiel Elliott",
        "Marquise Brown",
        "Darnell Mooney",
        "Aaron Rodgers",
        "Dallas Goedert",
        "James Robinson",
        "Daniel Carlson",
        "Diontae Johnson",
        "Geno Smith",
        "Jason Myers",
        "Broncos D/ST",
        "Joshua Palmer",
        "Parris Campbell",
        "Mecole Hardman",
        "Seahawks D/ST",
        "Kenyan Drake"
      ]
    },
    {
      "name": "Fleece Hall",
      "players": [
        "Justin Jefferson",
        "CeeDee Lamb",
        "Travis Etienne Jr.",
        "Justin Herbert",
        "Amon-Ra St. Brown",
        "Darren Waller",
        "Tyler Lockett",
        "Michael Carter",
        "Eagles D/ST",
        "Brandon Aiyuk",
        "Gerald Everett",
        "Kenneth Walker III",
        "Chuba Hubbard",
        "Daniel Jones",
        "Tyler Bass",
        "Odell Beckham Jr.",
        "Jeff Wilson Jr."
      ]
    },
    {
      "name": "STL Cookies",
      "players": [
        "Jonathan Taylor",
        "Keenan Allen",
        "Jerry Jeudy",
        "Jalen Hurts",
        "DeVonta Smith",
        "Jamaal Williams",
        "Curtis Samuel",
        "Julio Jones",
        "Rex Burkhead",
        "Zay Jones",
        "Robert Tonyan",
        "49ers D/ST",
        "Melvin Gordon III",
        "Eno Benjamin",
        "Cairo Santos",
        "Colts D/ST",
        "Tyler Conklin"
      ]
    },
    {
      "name": "Monday Night Fucking",
      "players": [
        "Alvin Kamara",
        "D'Andre Swift",
        "James Conner",
        "Jaylen Waddle",
        "DK Metcalf",
        "JuJu Smith-Schuster",
        "Adam Thielen",
        "Joe Burrow",
        "Cowboys D/ST",
        "David Njoku",
        "George Pickens",
        "Pat Freiermuth",
        "Cordarrelle Patterson",
        "Rachaad White",
        "Graham Gano",
        "Jimmy Garoppolo",
        "Jaylen Warren"
      ]
    },
    {
      "name": "The Gussy Bussy",
      "players": [
        "Joe Mixon",
        "Leonard Fournette",
        "Mark Andrews",
        "David Montgomery",
        "Mike Williams",
        "Gabe Davis",
        "Christian Kirk",
        "Deebo Samuel",
        "D'Onta Foreman",
        "Gus Edwards",
        "Evan McPherson",
        "Kyren Williams",
        "Kyle Pitts",
        "Justin Fields",
        "Deon Jackson",
        "Donovan Peoples-Jones",
        "Titans D/ST"
      ]
    },
    {
      "name": "Traitorious Toney",
      "players": [
        "Cooper Kupp",
        "Travis Kelce",
        "Mike Evans",
        "AJ Dillon",
        "Lamar Jackson",
        "Drake London",
        "Kareem Hunt",
        "Rondale Moore",
        "Romeo Doubs",
        "Aaron Jones",
        "Patriots D/ST",
        "Wan'Dale Robinson",
        "J.K. Dobbins",
        "Nick Folk",
        "Isiah Pacheco",
        "Kadarius Toney",
        "Nyheim Hines"
      ]
    },
    {
      "name": "Team Bu",
      "players": [
        "Najee Harris",
        "Ja'Marr Chase",
        "Michael Pittman Jr.",
        "Patrick Mahomes",
        "Terry McLaurin",
        "Elijah Mitchell",
        "Devin Singletary",
        "Miles Sanders",
        "T.J. Hockenson",
        "Chris Olave",
        "Chase Claypool",
        "Garrett Wilson",
        "Bills D/ST",
        "Tyler Higbee",
        "Antonio Gibson",
        "Kirk Cousins",
        "Harrison Butker"
      ]
    },
    {
      "name": "Let's go Brandin",
      "players": [
        "Christian McCaffrey",
        "Tyreek Hill",
        "A.J. Brown",
        "Brandin Cooks",
        "Chris Godwin",
        "Josh Jacobs",
        "Dak Prescott",
        "Zach Ertz",
        "Buccaneers D/ST",
        "Tua Tagovailoa",
        "Khalil Herbert",
        "Ryan Succop",
        "Rhamondre Stevenson",
        "Allen Robinson II",
        "Damien Harris",
        "Greg Dulcich",
        "Jarvis Landry"
      ]
    },
    {
      "name": "SHOW ME YO TDs",
      "players": [
        "Dalvin Cook",
        "Davante Adams",
        "Saquon Barkley",
        "Dameon Pierce",
        "Amari Cooper",
        "Tony Pollard",
        "Alexander Mattison",
        "Kyler Murray",
        "DeAndre Hopkins",
        "George Kittle",
        "Jakobi Meyers",
        "Taysom Hill",
        "Younghoe Koo",
        "Latavius Murray",
        "Ravens D/ST",
        "Saints D/ST"
      ]
    }
  ]
}
